nilql/__init__.py
nilql/nilql.py
nilql-0.0.0a11.dist-info/LICENSE
nilql-0.0.0a11.dist-info/METADATA
nilql-0.0.0a11.dist-info/WHEEL
nilql-0.0.0a11.dist-info/top_level.txt
nilql-0.0.0a11.dist-info/RECORD
