Metadata-Version: 2.2
Name: nilql
Version: 0.0.0a11
Summary: Library for working with encrypted data within nilDB queries and replies.
License: MIT
Project-URL: Repository, https://github.com/nillionnetwork/nilql-py
Requires-Python: >=3.9
License-File: LICENSE
Requires-Dist: bcl~=2.3
Requires-Dist: pailliers~=0.1
Provides-Extra: docs
Requires-Dist: toml~=0.10.2; extra == "docs"
Requires-Dist: sphinx~=5.0; extra == "docs"
Requires-Dist: sphinx-rtd-theme~=2.0.0; extra == "docs"
Provides-Extra: test
Requires-Dist: pytest~=8.2; extra == "test"
Requires-Dist: pytest-cov~=5.0; extra == "test"
Provides-Extra: lint
Requires-Dist: pylint~=3.2.0; extra == "lint"
Provides-Extra: coveralls
Requires-Dist: coveralls~=4.0; extra == "coveralls"
Provides-Extra: publish
Requires-Dist: build~=0.10; extra == "publish"
Requires-Dist: twine~=4.0; extra == "publish"
